README.rst
setup.py
marshmallow_form/__init__.py
marshmallow_form/boundfield.py
marshmallow_form/exceptions.py
marshmallow_form/langhelpers.py
marshmallow_form/layout.py
marshmallow_form/lazylist.py
marshmallow_form.egg-info/PKG-INFO
marshmallow_form.egg-info/SOURCES.txt
marshmallow_form.egg-info/dependency_links.txt
marshmallow_form.egg-info/entry_points.txt
marshmallow_form.egg-info/not-zip-safe
marshmallow_form.egg-info/pbr.json
marshmallow_form.egg-info/requires.txt
marshmallow_form.egg-info/top_level.txt
marshmallow_form/tests/__init__.py
marshmallow_form/tests/test_factory.py
marshmallow_form/tests/test_issued.py
marshmallow_form/tests/test_it.py
marshmallow_form/tests/test_layout.py
marshmallow_form/tests/test_many.py
marshmallow_form/tests/test_meta_fields.py
marshmallow_form/tests/test_validation.py