Metadata-Version: 1.1
Name: marshmallow-form
Version: 0.1.1
Summary: a wrapper of marshmallow for form library like behavior
Home-page: https://github.com/podhmo/marshmallow-form
Author: podhmo
Author-email: UNKNOWN
License: UNKNOWN
Keywords: marshmallow,form
Platform: UNKNOWN
Classifier: Programming Language :: Python
Classifier: Programming Language :: Python :: Implementation :: CPython
